taskw_ng/__init__.py
taskw_ng/__version__.py
taskw_ng/exceptions.py
taskw_ng/fields/__init__.py
taskw_ng/fields/annotationarray.py
taskw_ng/fields/array.py
taskw_ng/fields/base.py
taskw_ng/fields/choice.py
taskw_ng/fields/commaseparateduuid.py
taskw_ng/fields/date.py
taskw_ng/fields/duration.py
taskw_ng/fields/numeric.py
taskw_ng/fields/string.py
taskw_ng/fields/uuid.py
taskw_ng/py.typed
taskw_ng/task.py
taskw_ng/taskrc.py
taskw_ng/utils.py
taskw_ng/warrior.py
taskw_ng-0.2.7.dist-info/LICENSE.txt
taskw_ng-0.2.7.dist-info/METADATA
taskw_ng-0.2.7.dist-info/WHEEL
taskw_ng-0.2.7.dist-info/RECORD
