Metadata-Version: 2.1
Name: taskw-ng
Version: 0.2.7
Summary: Next generation python bindings for your taskwarrior database
Home-page: https://github.com/bergercookie/taskw-ng
License: GPLv3+
Keywords: taskwarrior,task
Author: Nikos Koukis
Author-email: nickkouk@gmail.com
Requires-Python: >=3.8,<4.0
Classifier: Development Status :: 5 - Production/Stable
Classifier: Intended Audience :: Developers
Classifier: License :: OSI Approved :: GNU General Public License (GPL)
Classifier: License :: Other/Proprietary License
Classifier: Programming Language :: Python :: 3
Classifier: Programming Language :: Python :: 3.8
Classifier: Programming Language :: Python :: 3.9
Classifier: Programming Language :: Python :: 3.10
Classifier: Programming Language :: Python :: 3.11
Classifier: Programming Language :: Python :: 3.12
Requires-Dist: kitchen (>=1.2.6,<2.0.0)
Requires-Dist: packaging (>=23.2,<24.0)
Requires-Dist: python-dateutil (>=2.8.2,<3.0.0)
Requires-Dist: pytz (>=2023.3.post1,<2024.0)
Project-URL: Repository, https://github.com/bergercookie/taskw-ng
